[
 {
    "q": "What were the three weapons in the combat sport of fencing?",
    "choices": [
      "Foil, Épée, Sabre",
      "Rapier, Cutlass, Scimitar",
      "Sword, Dagger, Pike",
      "Foil, Épée, Longsword"
    ],
    "aIndex": 0,
    "evidence": "page 1"
  },
  {
    "q": "What must you first learn as you begin your foil training?",
    "choices": [
      "Right-of-way",
      "How to grip the blade",
      "Advanced footwork patterns",
      "Equipment maintenance"
    ],
    "aIndex": 0,
    "evidence": "page 1"
  },
  {
    "q": "What is right-of-way in fencing?",
    "choices": [
      "The first person to establish a valid threat to their opponent’s target area",
      "Who moves first off the starting line",
      "Whose blade is longer",
      "Who steps over the boundary first"
    ],
    "aIndex": 0,
    "evidence": "page 1"
  },
  {
    "q": "What was awarded to the fencer who has the right-of-way?",
    "choices": [
      "The point",
      "A medal",
      "Extra time",
      "A redo of the action"
    ],
    "aIndex": 0,
    "evidence": "page 1"
  },
  {
    "q": "How many points did a fencer need to win the bout?",
    "choices": [
      "Fifteen points",
      "Ten points",
      "Twenty points",
      "Five points"
    ],
    "aIndex": 0,
    "evidence": "page 1"
  },
  {
    "q": "What was the name of Lucy’s school?",
    "choices": [
      "Butler Middle School",
      "Lincoln Middle School",
      "Maple Grove School",
      "Riverside School"
    ],
    "aIndex": 0,
    "evidence": "page 2"
  },
  {
    "q": "What could Lucy not believe she had to take on the first day of middle school?",
    "choices": [
      "The bus",
      "Her backpack",
      "The wrong bus",
      "The carpool"
    ],
    "aIndex": 0,
    "evidence": "page 2"
  },
  {
    "q": "How did Lucy wish she could get to school on her first day?",
    "choices": [
      "Her mom to drive her",
      "Ride a bicycle",
      "Walk with friends",
      "Take a skateboard"
    ],
    "aIndex": 0,
    "evidence": "page 2"
  },
  {
    "q": "What did Lucy think people were going to think of her for riding the bus?",
    "choices": [
      "That she’s a baby",
      "That she’s the teacher’s pet",
      "That she’s super cool",
      "That she’s late"
    ],
    "aIndex": 0,
    "evidence": "page 2"
  },
  {
    "q": "When Lucy got off the bus on the first day of school, what did she imagine the school looked like?",
    "choices": [
      "A castle",
      "A mansion",
      "A museum",
      "A maze"
    ],
    "aIndex": 0,
    "evidence": "page 4"
  },
  {
    "q": "What were the Hallway Etiquette rules at Lucy’s middle school?",
    "choices": [
      "No running, No swearing, No shouting and No eating",
      "No walking, No talking, No smiling and No phones",
      "No homework, No recess, No games and No snacks",
      "No clubs, No sports, No music and No art"
    ],
    "aIndex": 0,
    "evidence": "page 5"
  },
  {
    "q": "Who did Lucy see in the hallway on her first day of middle school?",
    "choices": [
      "Sasha",
      "GiGi",
      "Mia",
      "Anna"
    ],
    "aIndex": 0,
    "evidence": "page 6"
  },
  {
    "q": "What class was Sasha taking that is mostly 8th graders?",
    "choices": [
      "Drama",
      "Science",
      "Math",
      "Art"
    ],
    "aIndex": 0,
    "evidence": "page 7"
  },
  {
    "q": "What clubs did Lucy tell Sasha she was thinking about joining on the first day of school?",
    "choices": [
      "Art club, Chess team and Choir",
      "Drama, Fencing and Gardening",
      "Robotics, Soccer and Debate",
      "Cooking, Science and Book club"
    ],
    "aIndex": 0,
    "evidence": "page 7"
  },
  {
    "q": "What club did Sasha suggest Lucy join on the first day of school?",
    "choices": [
      "The fencing team",
      "The basketball team",
      "The chess club",
      "The gardening club"
    ],
    "aIndex": 0,
    "evidence": "page 7"
  },
 {
    "q": "Lucy is the only person Sasha knows who brought what on the first day of school?",
    "choices": [
      "Books",
      "A skateboard",
      "A bouquet of flowers",
      "Her lunch tray from home"
    ],
    "aIndex": 0,
    "evidence": "page 8"
  },
  {
    "q": "Who was Lucy hoping to avoid on the first day of middle school?",
    "choices": [
      "GiGi",
      "Sasha",
      "Mrs. Jones",
      "Damien Jo"
    ],
    "aIndex": 0,
    "evidence": "page 10"
  },
  {
    "q": "Who was GiGi?",
    "choices": [
      "Lucy’s older sister",
      "A new student",
      "The school librarian",
      "The fencing coach"
    ],
    "aIndex": 0,
    "evidence": "page 13"
  },
  {
    "q": "Where did Lucy run into GiGi on the first day of school?",
    "choices": [
      "In the cafeteria",
      "At the bus stop",
      "In the choir room",
      "In the library"
    ],
    "aIndex": 0,
    "evidence": "page 13"
  },
  {
    "q": "Why did GiGi tell Lucy she couldn’t sit with her?",
    "choices": [
      "It’s the 8th grade table",
      "She didn’t bring lunch",
      "Lucy was late",
      "The table was full"
    ],
    "aIndex": 0,
    "evidence": "page 13"
  },
  {
    "q": "Where did GiGi tell Lucy to send her a postcard from in the cafeteria on the first day of school?",
    "choices": [
      "Dorkville",
      "Coolville",
      "The library",
      "Sunny’s Ice Cream"
    ],
    "aIndex": 0,
    "evidence": "page 14"
  },
  {
    "q": "What did GiGi do to Lucy in the cafeteria on the first day of school?",
    "choices": [
      "She trips her",
      "She takes her seat",
      "She spills juice on her",
      "She hides her backpack"
    ],
    "aIndex": 0,
    "evidence": "page 15"
  },
  {
    "q": "What did GiGi say to Lucy as she tripped her in the cafeteria?",
    "choices": [
      "Enjoy the trip",
      "Watch your step",
      "Oops, my bad",
      "Walk faster, slowpoke"
    ],
    "aIndex": 0,
    "evidence": "page 14"
  },
  {
    "q": "As Lucy is falling after GiGi trips her, what was Lucy thinking about?",
    "choices": [
      "GiGi being mean when they were younger—ripping her doll, pushing her off the couch, scaring her, and saying she wished she was never born",
      "How to find her next class",
      "The lunch menu",
      "A joke Sasha told earlier"
    ],
    "aIndex": 0,
    "evidence": "pages 17-18"
  },
  {
    "q": "What did GiGi say to Lucy after she tripped her?",
    "choices": [
      "Don’t 6th graders even know how to walk?",
      "You should pay attention",
      "That table is reserved",
      "We’re going to be late"
    ],
    "aIndex": 0,
    "evidence": "page 20"
  },
  {
    "q": "What did Lucy pull out of GiGi’s bag after she was tripped in the cafeteria?",
    "choices": [
      "Her fencing sword",
      "Her math notebook",
      "A phone",
      "A diary"
    ],
    "aIndex": 0,
    "evidence": "page 21"
  },
  {
    "q": "What did Lucy say to GiGi after being tripped in the cafeteria?",
    "choices": [
      "I challenge you to a duel!",
      "Give that back!",
      "Leave me alone!",
      "You’re in trouble!"
    ],
    "aIndex": 0,
    "evidence": "page 22"
  },
  {
    "q": "GiGi said fencers don’t have duels—they have what?",
    "choices": [
      "Bouts",
      "Matches",
      "Rounds",
      "Challenges"
    ],
    "aIndex": 0,
    "evidence": "page 26"
  },
  {
    "q": "What happened after Lucy and GiGi argued in the cafeteria?",
    "choices": [
      "Both were sent to the principal’s office",
      "Lucy was sent home",
      "GiGi was suspended for a week",
      "They apologized immediately"
    ],
    "aIndex": 0,
    "evidence": "page 27"
  },
  {
    "q": "What was the blade action performed before the start of a bout called?",
    "choices": [
      "The Salute",
      "The Bow",
      "The Tap",
      "The Wave"
    ],
    "aIndex": 0,
    "evidence": "page 29"
  },
 {
    "q": "The salute is an action performed to acknowledge who?",
    "choices": [
      "Your opponent, referee and judges",
      "The audience",
      "Your coach and teammates",
      "The timekeeper and announcer"
    ],
    "aIndex": 0,
    "evidence": "page 29"
  },
  {
    "q": "What does the salute indicate?",
    "choices": [
      "Respect and good sportsmanship",
      "A victory celebration",
      "The start of a timeout",
      "A request for substitution"
    ],
    "aIndex": 0,
    "evidence": "page 29"
  },
  {
    "q": "What motion is used for the salute?",
    "choices": [
      "A sweeping motion across the face or from the face down in a counterclockwise motion in front of the body",
      "A quick bow at the waist",
      "Tapping blades three times",
      "Raising your mask hand straight up"
    ],
    "aIndex": 0,
    "evidence": "page 29"
  },
  {
    "q": "Not performing a salute is a sign of what?",
    "choices": [
      "Disrespect",
      "Exhaustion",
      "Nervousness",
      "Injury"
    ],
    "aIndex": 0,
    "evidence": "page 29"
  },
  {
    "q": "A salute signifies an agreement between opponents much like what?",
    "choices": [
      "The shaking of hands",
      "Signing a contract",
      "A high‑five",
      "A formal bow"
    ],
    "aIndex": 0,
    "evidence": "page 29"
  },
  {
    "q": "What color was the door to the principal’s office?",
    "choices": [
      "Green",
      "Blue",
      "Red",
      "Brown"
    ],
    "aIndex": 0,
    "evidence": "page 30"
  },
  {
    "q": "Before Lucy and GiGi saw the principal, who did they have to wait on?",
    "choices": [
      "Their mother to arrive",
      "The principal to return from lunch",
      "The school counselor",
      "Coach Leona"
    ],
    "aIndex": 0,
    "evidence": "page 32"
  },
  {
    "q": "Why did GiGi think Lucy read her diary?",
    "choices": [
      "It wasn’t where she left it, and there were scratch marks from trying to pick the lock",
      "Several pages were missing",
      "Lucy admitted she skimmed it",
      "Maddie said she saw Lucy reading it"
    ],
    "aIndex": 0,
    "evidence": "page 34"
  },
  {
    "q": "What was the Principal’s name?",
    "choices": [
      "Principal Olney",
      "Principal Carter",
      "Principal Green",
      "Principal Smith"
    ],
    "aIndex": 0,
    "evidence": "page 39"
  },
  {
    "q": "What was the name of GiGi and Lucy’s mother?",
    "choices": [
      "Mrs. Jones",
      "Mrs. Smith",
      "Ms. Pearson",
      "Mrs. Green"
    ],
    "aIndex": 0,
    "evidence": "page 37"
  },
  {
    "q": "Where did GiGi and Lucy’s mother work?",
    "choices": [
      "The hospital",
      "The salon",
      "The middle school",
      "The library"
    ],
    "aIndex": 0,
    "evidence": "page 37"
  },
  {
    "q": "What did GiGi wish when she was sitting in the principal’s office?",
    "choices": [
      "That she was invisible",
      "That she could go home early",
      "That she was team captain",
      "That Lucy would apologize"
    ],
    "aIndex": 0,
    "evidence": "page 37"
  },
  {
    "q": "Their mother told Principal Olney that the girls have been having issues getting along since when?",
    "choices": [
      "Their father passed away",
      "They moved neighborhoods",
      "They started middle school",
      "They joined the fencing team"
    ],
    "aIndex": 0,
    "evidence": "page 39"
  },
  {
    "q": "What did Butler Middle School have strict rules about?",
    "choices": [
      "Bullying",
      "Chewing gum",
      "Running in the halls",
      "Dress code violations"
    ],
    "aIndex": 0,
    "evidence": "page 41"
  },
  {
    "q": "According to the Athletic Code of Conduct, what should GiGi’s punishment be for the cafeteria fight?",
    "choices": [
      "She should be kicked off the team for having her foil in the cafeteria",
      "She should get detention only",
      "She should apologize in writing",
      "She should lose lunch privileges for a week"
    ],
    "aIndex": 0,
    "evidence": "page 42"
  },
  {
    "q": "Who did Principal Olney say the girls can talk to about their grief?",
    "choices": [
      "The school counselor",
      "The principal",
      "The school nurse",
      "The librarian"
    ],
    "aIndex": 0,
    "evidence": "page 45"
  },
  {
    "q": "When did GiGi tell Lucy she can go against her in fencing?",
    "choices": [
      "In three weeks, after captain tryouts",
      "The next day after school",
      "This weekend at practice",
      "At the end of the semester"
    ],
    "aIndex": 0,
    "evidence": "page 48"
  },
  {
    "q": "What did the sisters agree on after their meeting with the principal?",
    "choices": [
      "To not tell their mom about their fencing bout in three weeks",
      "To quit the fencing team together",
      "To apologize publicly in the cafeteria",
      "To switch homerooms to avoid each other"
    ],
    "aIndex": 0,
    "evidence": "page 51"
  },
  {
    "q": "What is the proper en garde stance?",
    "choices": [
      "Front foot pointed forward, back foot about 2–3 feet apart at a 90° angle",
      "Both feet together, knees locked, blade held straight up",
      "Back foot pointed forward with feet touching and shoulders square",
      "Feet parallel and wide, hands on hips to show readiness"
    ],
    "aIndex": 0,
    "evidence": "page 53"
  },
  {
    "q": "What does “en garde” mean in French?",
    "choices": [
      "On your guard",
      "Begin",
      "Good luck",
      "Stop"
    ],
    "aIndex": 0,
    "evidence": "page 53"
  },
  {
    "q": "Who speaks the words “en garde” during fencing?",
    "choices": [
      "The referee",
      "The team captain",
      "The coach",
      "The timekeeper"
    ],
    "aIndex": 0,
    "evidence": "page 53"
  },
  {
    "q": "What does “to be on guard” mean in fencing?",
    "choices": [
      "To be ready, poised for fighting either for attack or defense",
      "To relax and reset between actions",
      "To retreat to the end line",
      "To end the bout immediately"
    ],
    "aIndex": 0,
    "evidence": "page 53"
  },
  {
    "q": "When was the last time Lucy picked up a foil?",
    "choices": [
      "When her dad was alive",
      "Last summer at camp",
      "Earlier that morning",
      "She had never held one before"
    ],
    "aIndex": 0,
    "evidence": "page 54"
  },
  {
    "q": "Why couldn’t Sasha believe Lucy was going to fence GiGi?",
    "choices": [
      "She’s her sister, and GiGi is the best fencer in the school",
      "Lucy is allergic to metal and can’t wear gear",
      "Lucy is on the soccer team instead",
      "GiGi doesn’t even attend the school anymore"
    ],
    "aIndex": 0,
    "evidence": "page 55"
  },
  {
    "q": "What was the name of Butler Middle School’s librarian?",
    "choices": [
      "Mrs. Pearson",
      "Ms. Carter",
      "Mr. Sweet",
      "Mrs. Green"
    ],
    "aIndex": 0,
    "evidence": "page 56"
  },
  {
    "q": "What book did Sasha find that made her wonder why the library even has it?",
    "choices": [
      "Self‑defense with a cane",
      "Advanced Archery for Teens",
      "Ballet Basics for Beginners",
      "Medieval Spear Fighting"
    ],
    "aIndex": 0,
    "evidence": "page 56"
  },
  {
    "q": "Why did the fencing book Sasha found in the library upset Lucy?",
    "choices": [
      "It’s the same book her dad had",
      "Its cover was torn off",
      "The author criticized schools",
      "It was long overdue"
    ],
    "aIndex": 0,
    "evidence": "page 57"
  },
  {
    "q": "Why did Lucy think the man on the front of the fencing book looks ridiculous?",
    "choices": [
      "His pose isn’t how fencers really stand",
      "He’s wearing a superhero cape",
      "He’s holding two swords at once",
      "He’s fencing in sandals"
    ],
    "aIndex": 0,
    "evidence": "page 57"
  },
  {
    "q": "How long ago were the origins of fencing recorded?",
    "choices": [
      "As early as the 12th century in Egypt",
      "In the 5th century in Greece",
      "In the 18th century in France",
      "In the 3rd century in China"
    ],
    "aIndex": 0,
    "evidence": "page 57"
  },
  {
    "q": "When did fencing become an organized competitive sport?",
    "choices": [
      "The 19th century",
      "The 16th century",
      "The 17th century",
      "The 20th century"
    ],
    "aIndex": 0,
    "evidence": "page 57"
  }
]
